totp_auth/__init__.py
totp_auth/cli.py
totp_auth/cookie.py
totp_auth/login.html
totp_auth/server.py
totp_auth/utils.py
totp_auth/classes/__init__.py
totp_auth/classes/db_config.py
totp_auth/classes/http_request.py
totp_auth/classes/page_loader.py
totp_auth/migrations/1.sql
totp_auth/migrations/_default.sql
totp_auth-1.1.21.dist-info/LICENSE
totp_auth-1.1.21.dist-info/METADATA
totp_auth-1.1.21.dist-info/WHEEL
totp_auth-1.1.21.dist-info/entry_points.txt
totp_auth-1.1.21.dist-info/top_level.txt
totp_auth-1.1.21.dist-info/RECORD
